cosmic/Match.py
cosmic/__init__.py
cosmic/_commit_hash.py
cosmic/_evolvebin.cpython-313-x86_64-linux-gnu.so
cosmic/_version.py
cosmic/checkstate.py
cosmic/evolve.py
cosmic/filter.py
cosmic/get_commit_hash.py
cosmic/output.py
cosmic/plotting.py
cosmic/test_evolve.py
cosmic/test_match.py
cosmic/test_sample.py
cosmic/test_utils.py
cosmic/utils.py
cosmic/bse_utils/__init__.py
cosmic/bse_utils/zcnsts.py
cosmic/bse_utils/zdata.py
cosmic/data/cosmic-settings.json
cosmic/sample/__init__.py
cosmic/sample/initialbinarytable.py
cosmic/sample/initialcmctable.py
cosmic/sample/cmc/__init__.py
cosmic/sample/cmc/elson.py
cosmic/sample/cmc/king.py
cosmic/sample/sampler/__init__.py
cosmic/sample/sampler/cmc.py
cosmic/sample/sampler/independent.py
cosmic/sample/sampler/multidim.py
cosmic/sample/sampler/sampler.py
cosmic_popsynth-3.6.2.data/scripts/cosmic-pop
cosmic_popsynth.libs/libgfortran-040039e1.so.5.0.0
cosmic_popsynth.libs/libquadmath-96973f99.so.0.0.0
cosmic_popsynth-3.6.2.dist-info/METADATA
cosmic_popsynth-3.6.2.dist-info/WHEEL
cosmic_popsynth-3.6.2.dist-info/RECORD
cosmic_popsynth-3.6.2.dist-info/sboms/auditwheel.cdx.json
