Metadata-Version: 2.1
Name: cosmic-popsynth
Version: 3.6.2
Summary: a Python-interfaced binary population synthesis suite
Author: Scott Coughlin, Michael Zevin, Carl L. Rodriguez, Tom Wagg
Author-Email: Katelyn Breivik <katie.breivik@gmail.com>
License: MIT License
Classifier: Development Status :: 5 - Production/Stable
Classifier: Intended Audience :: Developers
Classifier: Intended Audience :: Science/Research
Classifier: License :: OSI Approved :: MIT License
Classifier: Operating System :: OS Independent
Classifier: Programming Language :: Python
Requires-Python: >=3.10
Requires-Dist: numpy
Requires-Dist: scipy
Requires-Dist: astropy
Requires-Dist: configparser
Requires-Dist: tqdm
Requires-Dist: pandas
Requires-Dist: tables
Requires-Dist: h5py
Requires-Dist: schwimmbad
Requires-Dist: matplotlib
